moban/__init__.py
moban/__main__.py
moban/_version.py
moban/constants.py
moban/exceptions.py
moban/main.py
moban/program_options.py
moban/core/__init__.py
moban/core/content_processor.py
moban/core/context.py
moban/core/data_loader.py
moban/core/definitions.py
moban/core/hashstore.py
moban/core/moban_factory.py
moban/core/plugins.py
moban/core/strategy.py
moban/core/utils.py
moban/core/mobanfile/__init__.py
moban/core/mobanfile/store.py
moban/core/mobanfile/targets.py
moban/core/mobanfile/templates.py
moban/deprecated/__init__.py
moban/deprecated/library.py
moban/deprecated/repo.py
moban/externals/__init__.py
moban/externals/buffered_writer.py
moban/externals/file_system.py
moban/externals/reporter.py
moban/plugins/__init__.py
moban/plugins/copy.py
moban/plugins/delete.py
moban/plugins/json_loader.py
moban/plugins/strip.py
moban/plugins/yaml_loader.py
moban/plugins/jinja2/__init__.py
moban/plugins/jinja2/engine.py
moban/plugins/jinja2/extensions.py
moban/plugins/jinja2/filters/__init__.py
moban/plugins/jinja2/filters/repr.py
moban/plugins/jinja2/filters/text.py
moban-0.8.2.dist-info/LICENSE
moban-0.8.2.dist-info/METADATA
moban-0.8.2.dist-info/WHEEL
moban-0.8.2.dist-info/entry_points.txt
moban-0.8.2.dist-info/top_level.txt
moban-0.8.2.dist-info/RECORD
