Metadata-Version: 2.1
Name: moban
Version: 0.8.2
Summary: General purpose static text generator
Home-page: https://github.com/moremoban/moban
Author: chfw
Author-email: wangc_2011@hotmail.com
License: MIT
Download-URL: https://github.com/moremoban/moban/archive/0.8.2.tar.gz
Keywords: python,jinja2,moban
Platform: UNKNOWN
Classifier: Topic :: Software Development :: Libraries
Classifier: Programming Language :: Python
Classifier: Intended Audience :: Developers
Classifier: Programming Language :: Python :: 3 :: Only
Classifier: Programming Language :: Python :: 3.6
Classifier: Programming Language :: Python :: 3.7
Classifier: Programming Language :: Python :: 3.8
Requires-Python: >=3.6
Requires-Dist: jinja2 (>=2.7.1)
Requires-Dist: lml (>=0.0.9)
Requires-Dist: appdirs (>=1.4.3)
Requires-Dist: crayons (>=0.1.0)
Requires-Dist: fs (>=2.4.11)
Requires-Dist: jinja2-fsloader (>=0.2.0)
Requires-Dist: moban-jinja2-github
Requires-Dist: ruamel.yaml (>=0.15.5) ; python_version != '3.4' and python_version < '3.7'
Requires-Dist: ruamel.yaml (>=0.15.42) ; python_version == '3.7'
Requires-Dist: ruamel.yaml (>=0.15.98) ; python_version == '3.8'
